base10/__init__.py
base10/base.py
base10/exceptions.py
base10/helpers.py
base10/dialects/__init__.py
base10/dialects/influxdb_dialect.py
base10/dialects/json_dialect.py
base10/dialects/splunk_dialect.py
base10/test/__init__.py
base10/test/test_base.py
base10/test/test_exceptions.py
base10/test/test_helpers.py
base10/transports/__init__.py
base10/transports/file_transport.py
base10/transports/rabbitmq_transport.py
base10/transports/udp_transport.py
base10-0.6.3.dist-info/DESCRIPTION.rst
base10-0.6.3.dist-info/METADATA
base10-0.6.3.dist-info/RECORD
base10-0.6.3.dist-info/WHEEL
base10-0.6.3.dist-info/metadata.json
base10-0.6.3.dist-info/top_level.txt
