Metadata-Version: 2.0
Name: base10
Version: 0.6.3
Summary: Base10 is a metrics abstractoin layer for linking multiple metrics source and stores. It also simplifies metric creation and proxying.
Home-page: https://github.com/mattdavis90/base10
Author: Matt Davis
Author-email: mattdavis90@googlemail.com
License: MIT
Platform: UNKNOWN
Classifier: License :: OSI Approved :: MIT License
Classifier: Programming Language :: Python :: 2
Classifier: Programming Language :: Python :: 2.7
Classifier: Programming Language :: Python :: 3
Classifier: Programming Language :: Python :: 3.2
Classifier: Programming Language :: Python :: 3.3
Classifier: Programming Language :: Python :: 3.4
Classifier: Programming Language :: Python :: Implementation :: CPython
Classifier: Programming Language :: Python :: Implementation :: PyPy
Requires-Dist: six
